osmgeocoder/__init__.py
osmgeocoder/format.py
osmgeocoder/forward.py
osmgeocoder/geocoder.py
osmgeocoder/reverse.py
osmgeocoder/data/config-example.json
osmgeocoder/data/imposm_mapping.yml
osmgeocoder/data/worldwide.yml
osmgeocoder/data/sql/geocoder/001-wordlist_for_text_prediction.sql
osmgeocoder/data/sql/geocoder/002-text_prediction.sql
osmgeocoder/data/sql/geocoder/003-forward_geocoding.sql
osmgeocoder/data/sql/geocoder/004-reverse_geocoding.sql
osmgeocoder/data/sql/optimize/001-osm_house_number_to_struct_house.sql
osmgeocoder/data/sql/optimize/002-osm_buildings_to_struct_house.sql
osmgeocoder/data/sql/optimize/003-struct_house_index.sql
osmgeocoder/data/sql/optimize/004-fill_street_only_entries.sql
osmgeocoder/data/sql/optimize/005-fill_postcode_only_entries.sql
osmgeocoder/data/sql/optimize/006-extract_cities.sql
osmgeocoder/data/sql/optimize/007-index_cities.sql
osmgeocoder/data/sql/optimize/008-update_struct_house_with_city.sql
osmgeocoder/data/sql/optimize/009-extract_streets.sql
osmgeocoder/data/sql/optimize/010-index_streets.sql
osmgeocoder/data/sql/optimize/011-update_struct_house_with_street.sql
osmgeocoder/data/sql/optimize/012-geometry_for_streets.sql
osmgeocoder/data/sql/optimize/013-geometry_for_cities.sql
osmgeocoder/data/sql/optimize/014-cleanup_struct_house_table.sql
osmgeocoder/data/sql/optimize/015-cluster_struct_house_table.sql
osmgeocoder/data/sql/optimize/016-add_indices_to_struct_tables.sql
osmgeocoder/data/sql/optimize/017-update_city_names_from_osm.sql
osmgeocoder/data/sql/optimize/018-manual_city_name_updates.sql
osmgeocoder/data/sql/prepare/001-custom_types.sql
osmgeocoder-2.1.0.data/scripts/address2coordinate.py
osmgeocoder-2.1.0.data/scripts/coordinate2address.py
osmgeocoder-2.1.0.data/scripts/finalize_geocoder.py
osmgeocoder-2.1.0.data/scripts/geocoder_service.py
osmgeocoder-2.1.0.data/scripts/import_openaddress_data.py
osmgeocoder-2.1.0.data/scripts/postal_service.py
osmgeocoder-2.1.0.data/scripts/prepare_osm.py
osmgeocoder-2.1.0.dist-info/LICENSE.txt
osmgeocoder-2.1.0.dist-info/METADATA
osmgeocoder-2.1.0.dist-info/WHEEL
osmgeocoder-2.1.0.dist-info/top_level.txt
osmgeocoder-2.1.0.dist-info/RECORD
