Metadata-Version: 2.1
Name: osmgeocoder
Version: 2.1.0
Summary: OpenStreetMap and OpenAddresses.io based geocoder
Home-page: https://github.com/dunkelstern/osmgeocoder
Author: Johannes Schriewer
Author-email: hallo@dunkelstern.de
License: LICENSE.txt
Keywords: osm openstreetmap geocoding geocoder openaddresses.io
Platform: UNKNOWN
Classifier: Development Status :: 5 - Production/Stable
Classifier: Intended Audience :: Developers
Classifier: License :: OSI Approved :: BSD License
Classifier: Programming Language :: Python
Classifier: Programming Language :: Python :: 3
Classifier: Programming Language :: Python :: 3.7
Classifier: Programming Language :: Python :: 3.8
Classifier: Programming Language :: Python :: 3.9
Classifier: Programming Language :: Python :: 3.10
Classifier: Operating System :: OS Independent
License-File: LICENSE.txt
Requires-Dist: psycopg2 (>=2.8)
Requires-Dist: pyproj (>=1.9)
Requires-Dist: Shapely (>=1.6)
Requires-Dist: requests (>=2.18)
Requires-Dist: PyYAML (>=5.0)
Requires-Dist: pystache (>=0.5)
Requires-Dist: python-geohash (>=0.8.5)
